LICENSE
README.txt
cfcrypt/__init__.py
cfcrypt/_crypt_file.py
cfcrypt/constants.py
cfcrypt/crypt_file.py
cfcrypt/exceptions.py
cfcrypt/file_format.py
cfcrypt/file_utils.py
cfcrypt/keyring/__init__.py
cfcrypt/keyring/keyring.py
cfcrypt/message_authentication.py
cfcrypt/rsa/__init__.py
cfcrypt/rsa/exceptions.py
cfcrypt/rsa/high_level.py
cfcrypt/rsa/key_helpers.py
cfcrypt/rsa/low_level.py
cfcrypt/rsa/types.py
cf_crypt-0.1.1.dist-info/LICENSE
cf_crypt-0.1.1.dist-info/WHEEL
cf_crypt-0.1.1.dist-info/METADATA
cf_crypt-0.1.1.dist-info/RECORD
