Metadata-Version: 2.1
Name: cf-crypt
Version: 0.1.1
Summary: Encryption at rest made easy
Home-page: https://cf-crypt.readthedocs.io/en/latest/quickstart.html
License: MIT
Author: Keir Rice
Author-email: keir@clayfox.co.nz
Requires-Python: >=3.6,<4.0
Classifier: License :: OSI Approved :: MIT License
Classifier: Operating System :: OS Independent
Classifier: Programming Language :: Python :: 3
Classifier: Programming Language :: Python :: 3.6
Classifier: Programming Language :: Python :: 3.7
Classifier: Programming Language :: Python :: 3.8
Classifier: Programming Language :: Python :: 3.9
Classifier: Topic :: Software Development :: Libraries :: Python Modules
Requires-Dist: cf-json (>=0.1.0,<0.2.0)
Requires-Dist: cryptography (>=3.4.7,<3.5.0)
Requires-Dist: pathlib3x (>=1.3.9,<2.0.0); python_version < "3.8"
Project-URL: Bug Tracker, https://gitlab.clayfox.co.nz/cf/cf-crypt/-/issues
Project-URL: Documentation, https://cf-crypt.readthedocs.io/en/latest/
Project-URL: Repository, https://gitlab.clayfox.co.nz/cf/cf-crypt
